MANIFEST.in
README.md
setup.py
EVT_CAN_Tools.egg-info/PKG-INFO
EVT_CAN_Tools.egg-info/SOURCES.txt
EVT_CAN_Tools.egg-info/dependency_links.txt
EVT_CAN_Tools.egg-info/not-zip-safe
EVT_CAN_Tools.egg-info/top_level.txt
dbc-files/INTEL_EVT_CAN.dbc
evtcantools/__init__.py
evtcantools/dbcparser.py