Metadata-Version: 1.0
Name: EVT-CAN-Tools
Version: 0.1.0
Summary: Tools shared across software projects
Home-page: https://bitbucket.org/evt/evt-can-tools
Author: EVT RIT
Author-email: EVT@RIT.EDU
License: MIT
Platform: UNKNOWN
